adafruit_ble_radio.py
adafruit_circuitpython_ble_radio-0.5.15.dist-info/licenses/LICENSE
adafruit_circuitpython_ble_radio-0.5.15.dist-info/METADATA
adafruit_circuitpython_ble_radio-0.5.15.dist-info/WHEEL
adafruit_circuitpython_ble_radio-0.5.15.dist-info/top_level.txt
adafruit_circuitpython_ble_radio-0.5.15.dist-info/RECORD
