Metadata-Version: 2.4
Name: adafruit-circuitpython-ble-radio
Version: 0.5.15
Summary: Simple byte and string based inter-device communication via BLE.
Author-email: Adafruit Industries <circuitpython@adafruit.com>
License: MIT
Project-URL: Homepage, https://github.com/adafruit/Adafruit_CircuitPython_BLE_Radio
Keywords: adafruit,blinka,circuitpython,micropython,radio,ble
Classifier: Intended Audience :: Developers
Classifier: Topic :: Software Development :: Libraries
Classifier: Topic :: Software Development :: Embedded Systems
Classifier: Topic :: System :: Hardware
Classifier: License :: OSI Approved :: MIT License
Classifier: Programming Language :: Python :: 3
License-File: LICENSE
Requires-Dist: Adafruit-Blinka
Requires-Dist: adafruit-circuitpython-ble
Provides-Extra: optional
Dynamic: license-file
